[
  {
    "parcelType": 103,
    "parcels": [
      {
        "parcelNumber": 88155473008601,
        "weight": null,
        "volume": null,
        "additionalServices": [
          {
            "code": "ODK",
            "amount": null
          },
          {
            "code": "V",
            "amount": 39.9
          },
          {
            "code": "PR",
            "amount": null
          }
        ],
        "cn23": null,
        "international": {
          "nonDeliveryInstruction": 1,
          "categoryType": 5,
          "categoryExplanation": null,
          "importer": null,
          "importerPhone": null,
          "importerEmail": null,
          "comments": null,
          "license": null,
          "certificate": null,
          "invoice": null,
          "codForeign": null,
          "codForeignCurrency": "CDN"
        },
        "parcelContent": 1
      }
    ],
    "commonServices": null,
    "addressee": {
      "addresseeName1": "Hesham H. H. Mohammed",
      "addresseeName2": "Hesham",
      "addresseeAddress": "77 Citation Crescent",
      "addresseePostId": "L9K 1H8",
      "addresseePost": "Ancaster",
      "addresseeCountryId": "124",
      "addresseePhone": 9055125645,
      "addresseeEmail": "1mp1y9hswrlcw61@marketplace.amazon.ca"
    },
    "upn": null,
    "comment1": "Ontario",
    "comment2": "Pocket_Coffee_18_FBM",
    "recordNumber": "702-1977739-6933837"
  },
  {
    "parcelType": 103,
    "parcels": [
      {
        "parcelNumber": 88155755800361,
        "weight": null,
        "volume": null,
        "additionalServices": [
          {
            "code": "ODK",
            "amount": null
          },
          {
            "code": "V",
            "amount": 63.9
          },
          {
            "code": "PR",
            "amount": null
          }
        ],
        "cn23": null,
        "international": {
          "nonDeliveryInstruction": 1,
          "categoryType": 5,
          "categoryExplanation": null,
          "importer": null,
          "importerPhone": null,
          "importerEmail": null,
          "comments": null,
          "license": null,
          "certificate": null,
          "invoice": null,
          "codForeign": null,
          "codForeignCurrency": "CDN"
        },
        "parcelContent": 1
      }
    ],
    "commonServices": null,
    "addressee": {
      "addresseeName1": "Joseph Muglia",
      "addresseeName2": "Joseph",
      "addresseeAddress": "72 Radisson Dr",
      "addresseePostId": "K0A 1W0",
      "addresseePost": "Embrun",
      "addresseeCountryId": "124",
      "addresseePhone": 6136142795,
      "addresseeEmail": "t32lm9yzh6htrbd@marketplace.amazon.ca"
    },
    "upn": null,
    "comment1": "Ontario",
    "comment2": "BE-36D5-MFGZ",
    "recordNumber": "702-6404705-5881054"
  },
  {
    "parcelType": 103,
    "parcels": [
      {
        "parcelNumber": 88154905675921,
        "weight": null,
        "volume": null,
        "additionalServices": [
          {
            "code": "ODK",
            "amount": null
          },
          {
            "code": "V",
            "amount": 73.9
          },
          {
            "code": "PR",
            "amount": null
          }
        ],
        "cn23": null,
        "international": {
          "nonDeliveryInstruction": 1,
          "categoryType": 5,
          "categoryExplanation": null,
          "importer": null,
          "importerPhone": null,
          "importerEmail": null,
          "comments": null,
          "license": null,
          "certificate": null,
          "invoice": null,
          "codForeign": null,
          "codForeignCurrency": "CDN"
        },
        "parcelContent": 1
      }
    ],
    "commonServices": null,
    "addressee": {
      "addresseeName1": "Maryam Askari",
      "addresseeName2": "maryam",
      "addresseeAddress": "44 Coldstream Run",
      "addresseePostId": "B2W 0A3",
      "addresseePost": "Dartmouth",
      "addresseeCountryId": "124",
      "addresseePhone": 9024405218,
      "addresseeEmail": "82yc7pjq6mrk6hg@marketplace.amazon.ca"
    },
    "upn": null,
    "comment1": "Nova Scotia",
    "comment2": "pocket_coffee_FBM_12-5",
    "recordNumber": "701-1043328-3249042"
  }
]